synoindexwatcher/__init__.py
synoindexwatcher/__main__.py
synoindexwatcher/constants.py
synoindexwatcher/files.py
synoindexwatcher-0.11.5.dist-info/LICENSE
synoindexwatcher-0.11.5.dist-info/METADATA
synoindexwatcher-0.11.5.dist-info/WHEEL
synoindexwatcher-0.11.5.dist-info/top_level.txt
synoindexwatcher-0.11.5.dist-info/RECORD
