Metadata-Version: 2.1
Name: synoindexwatcher
Version: 0.11.5
Summary: An automated media-index updater for Synology DiskStations based on inotify and synoindex.
Home-page: https://github.com/letorbi/synoindexwatcher
Author: Torben Haase
Author-email: git@letorbi.com
Classifier: Development Status :: 4 - Beta
Classifier: Environment :: Console
Classifier: Intended Audience :: System Administrators
Classifier: License :: OSI Approved :: GNU General Public License (GPL)
Classifier: Operating System :: POSIX :: Linux
Classifier: Programming Language :: Python :: 2.7
Classifier: Programming Language :: Python :: 3
Requires-Python: >=2.7, !=3.0.*, !=3.1.*
License-File: LICENSE
Requires-Dist: inotifyrecursive (>=0.3.5)
Requires-Dist: configparser ; python_version < "3.5"
